ENPMDA/ENPMDA.py
ENPMDA/__init__.py
ENPMDA/analysis/__init__.py
ENPMDA/analysis/analysis.py
ENPMDA/analysis/base.py
ENPMDA/preprocessing/__init__.py
ENPMDA/preprocessing/alignment.py
ENPMDA/preprocessing/trajectory_preprocessing.py
ENPMDA/utils/__init__.py
ENPMDA/utils/grouphug.py
ENPMDA/utils/utils.py
enpmda-1.0.0.dist-info/licenses/AUTHORS.rst
enpmda-1.0.0.dist-info/licenses/LICENSE
enpmda-1.0.0.dist-info/METADATA
enpmda-1.0.0.dist-info/WHEEL
enpmda-1.0.0.dist-info/top_level.txt
enpmda-1.0.0.dist-info/RECORD
