Metadata-Version: 2.4
Name: ENPMDA
Version: 1.0.0
Summary: Parallel analysis for ensemble simulations
Home-page: https://github.com/yuxuanzhuang/ENPMDA
Author: Yuxuan Zhuang
Author-email: Yuxuan Zhuang <wsygzyx@gmail.com>
License: GNU General Public License v3
Project-URL: Homepage, https://github.com/yuxuanzhuang/ENPMDA
Project-URL: Issues, https://github.com/yuxuanzhuang/ENPMDA/issues
Keywords: ENPMDA,MDAnalysis,Dask,molecular-dynamics
Classifier: Development Status :: 3 - Alpha
Classifier: Intended Audience :: Developers
Classifier: Intended Audience :: Science/Research
Classifier: License :: OSI Approved :: GNU General Public License v3 (GPLv3)
Classifier: Natural Language :: English
Classifier: Programming Language :: Python :: 3 :: Only
Classifier: Programming Language :: Python :: 3.10
Classifier: Programming Language :: Python :: 3.11
Classifier: Programming Language :: Python :: 3.12
Classifier: Topic :: Scientific/Engineering
Classifier: Topic :: Software Development :: Libraries :: Python Modules
Requires-Python: >=3.10
License-File: LICENSE
License-File: AUTHORS.rst
Requires-Dist: MDAnalysis>=2.8.0
Requires-Dist: dask[dataframe]>=2024.1.0
Requires-Dist: distributed>=2024.1.0
Requires-Dist: numpy>=1.23
Requires-Dist: pandas>=1.5
Requires-Dist: loguru
Provides-Extra: tests
Requires-Dist: pytest>=7; extra == "tests"
Requires-Dist: pytest-xdist>=3; extra == "tests"
Requires-Dist: numpy; extra == "tests"
Dynamic: author
Dynamic: home-page
Dynamic: license-file
Dynamic: requires-python
